network_finder/network_finder.cpython-37m-x86_64-linux-gnu.so
network_finder/__init__.py
network_finder/network_finder.py
network_finder-0.6.dist-info/WHEEL
network_finder-0.6.dist-info/METADATA
network_finder-0.6.dist-info/top_level.txt
network_finder-0.6.dist-info/LICENSE.md
network_finder-0.6.dist-info/RECORD
