Metadata-Version: 2.1
Name: network-finder
Version: 0.6
Summary: Matches IP addresses to encompassing networks
Home-page: https://github.com/bbayles/network-finder
Author: Bo Bayles
Author-email: bbayles@gmail.com
License: MIT
Platform: UNKNOWN
Classifier: Intended Audience :: Developers
Classifier: Intended Audience :: Information Technology
Classifier: Intended Audience :: System Administrators
Classifier: License :: OSI Approved :: Apache Software License
Classifier: Programming Language :: Python :: 3
